{
  "server": {
    "modified": 1734023548,
    "versions": {
      "stable": {
        "version": "1.16.0",
        "npm": "npm i @minecraft/server@1.16.0",
        "download": "https://registry.npmjs.org/@minecraft/server/-/server-1.16.0.tgz"
      },
      "stable_exp": {
        "version": "1.17.0-beta.1.21.51-stable",
        "npm": "npm i @minecraft/server@1.17.0-beta.1.21.51-stable",
        "download": "https://registry.npmjs.org/@minecraft/server/-/server-1.17.0-beta.1.21.51-stable.tgz"
      },
      "preview": {
        "version": "1.17.0-rc.1.21.60-preview.24",
        "npm": "npm i @minecraft/server@1.17.0-rc.1.21.60-preview.24",
        "download": "https://registry.npmjs.org/@minecraft/server/-/server-1.17.0-rc.1.21.60-preview.24.tgz"
      },
      "preview_exp": {
        "version": "1.18.0-beta.1.21.60-preview.24",
        "npm": "npm i @minecraft/server@1.18.0-beta.1.21.60-preview.24",
        "download": "https://registry.npmjs.org/@minecraft/server/-/server-1.18.0-beta.1.21.60-preview.24.tgz"
      }
    }
  },
  "server-ui": {
    "modified": 1734023516,
    "versions": {
      "stable": {
        "version": "1.3.0",
        "npm": "npm i @minecraft/server-ui@1.3.0",
        "download": "https://registry.npmjs.org/@minecraft/server-ui/-/server-ui-1.3.0.tgz"
      },
      "stable_exp": {
        "version": "1.4.0-beta.1.21.51-stable",
        "npm": "npm i @minecraft/server-ui@1.4.0-beta.1.21.51-stable",
        "download": "https://registry.npmjs.org/@minecraft/server-ui/-/server-ui-1.4.0-beta.1.21.51-stable.tgz"
      },
      "preview": {
        "version": "1.3.0-rc.1.21.40-preview.21",
        "npm": "npm i @minecraft/server-ui@1.3.0-rc.1.21.40-preview.21",
        "download": "https://registry.npmjs.org/@minecraft/server-ui/-/server-ui-1.3.0-rc.1.21.40-preview.21.tgz"
      },
      "preview_exp": {
        "version": "1.4.0-beta.1.21.60-preview.24",
        "npm": "npm i @minecraft/server-ui@1.4.0-beta.1.21.60-preview.24",
        "download": "https://registry.npmjs.org/@minecraft/server-ui/-/server-ui-1.4.0-beta.1.21.60-preview.24.tgz"
      }
    }
  },
  "server-gametest": {
    "modified": 1734023493,
    "versions": {
      "stable": {
        "version": "0.1.0",
        "npm": "npm i @minecraft/server-gametest@0.1.0",
        "download": "https://registry.npmjs.org/@minecraft/server-gametest/-/server-gametest-0.1.0.tgz"
      },
      "stable_exp": {
        "version": "1.0.0-beta.1.21.51-stable",
        "npm": "npm i @minecraft/server-gametest@1.0.0-beta.1.21.51-stable",
        "download": "https://registry.npmjs.org/@minecraft/server-gametest/-/server-gametest-1.0.0-beta.1.21.51-stable.tgz"
      },
      "preview": {
        "version": "0.1.0-rc.1.21.40-preview.20",
        "npm": "npm i @minecraft/server-gametest@0.1.0-rc.1.21.40-preview.20",
        "download": "https://registry.npmjs.org/@minecraft/server-gametest/-/server-gametest-0.1.0-rc.1.21.40-preview.20.tgz"
      },
      "preview_exp": {
        "version": "1.0.0-beta.1.21.60-preview.24",
        "npm": "npm i @minecraft/server-gametest@1.0.0-beta.1.21.60-preview.24",
        "download": "https://registry.npmjs.org/@minecraft/server-gametest/-/server-gametest-1.0.0-beta.1.21.60-preview.24.tgz"
      }
    }
  },
  "last_fetch": 1735607512
}
